dash_multipage/__init__.py
dash_multipage/callbacks.py
dash_multipage/controller_base.py
dash_multipage/multipage_controller.py
dash_multipage/url_arg_manager.py
dash_multipage/version.py
dash_multipage-1.0.1.dist-info/DESCRIPTION.rst
dash_multipage-1.0.1.dist-info/METADATA
dash_multipage-1.0.1.dist-info/RECORD
dash_multipage-1.0.1.dist-info/WHEEL
dash_multipage-1.0.1.dist-info/metadata.json
dash_multipage-1.0.1.dist-info/top_level.txt
