Metadata-Version: 2.0
Name: dash-multipage
Version: 1.0.1
Summary: A framework to simplify some of the challenges in setting up multipage dash pages.
Home-page: https://github.com/axlan/dash-multipage
Author: Jonathan Diamond
Maintainer: Jonathan Diamond
License: MIT
Project-URL: Documentation, https://github.com/axlan/dash-multipage
Project-URL: Code, https://github.com/axlan/dash-multipage
Project-URL: Issue tracker, https://github.com/axlan/dash-multipage/issues
Platform: UNKNOWN
Classifier: Development Status :: 4 - Beta
Classifier: Intended Audience :: Developers
Classifier: Programming Language :: Python
Classifier: Programming Language :: Python :: 3
Classifier: Programming Language :: Python :: 3.6
Classifier: Topic :: Software Development
Requires-Dist: dash
Requires-Dist: dash-html-components
Requires-Dist: dash-core-components
